serial_to_parallel_project/src/serial_to_parallel.v
module serial_to_parallel (
    input clk,
    input reset,
    input serial_in,
    output reg [3:0] parallel_out
);

always @(posedge clk or posedge reset)
begin
    if (reset)
        parallel_out <= 4'b0000;
    else
        parallel_out <= {parallel_out[2:0], serial_in};
end

endmodule

serial_to_parallel_project/tb/serial_to_parallel_tb.v
`timescale 1ns/1ps

module serial_to_parallel_tb;

reg clk;
reg reset;
reg serial_in;

wire [3:0] parallel_out;

serial_to_parallel uut (
    .clk(clk),
    .reset(reset),
    .serial_in(serial_in),
    .parallel_out(parallel_out)
);

initial begin
    $dumpfile("wave.vcd");
    $dumpvars(0, serial_to_parallel_tb);

    clk = 0;
    reset = 1;
    serial_in = 0;

    #10 reset = 0;

    #10 serial_in = 1;
    #10 serial_in = 0;
    #10 serial_in = 1;
    #10 serial_in = 1;

    #40 $finish;
end

always #5 clk = ~clk;

endmodule

serial_to_parallel_project/sim/wave.vcd
$date
	Mon Apr 20 23:23:33 2026
$end
$version
	Icarus Verilog
$end
$timescale
	1ps
$end
$scope module serial_to_parallel_tb $end
$var wire 4 ! parallel_out [3:0] $end
$var reg 1 " clk $end
$var reg 1 # reset $end
$var reg 1 $ serial_in $end
$scope module uut $end
$var wire 1 " clk $end
$var wire 1 # reset $end
$var wire 1 $ serial_in $end
$var reg 4 % parallel_out [3:0] $end
$upscope $end
$upscope $end
$enddefinitions $end
$comment Show the parameter values. $end
$dumpall
$end
#0
$dumpvars
b0 %
0$
1#
0"
b0 !
$end
#5000
1"
#10000
0"
0#
#15000
1"
#20000
0"
1$
#25000
b1 !
b1 %
1"
#30000
0"
0$
#35000
b10 !
b10 %
1"
#40000
0"
1$
#45000
b101 !
b101 %
1"
#50000
0"
#55000
b1011 !
b1011 %
1"
#60000
0"
#65000
b111 !
b111 %
1"
#70000
0"
#75000
b1111 !
b1111 %
1"
